py_in_win_exe/__init__.py
py_in_win_exe/cli.py
py_in_win_exe/compiler.py
py_in_win_exe/gui.py
py_in_win_exe-1.0.2.dist-info/licenses/LICENSE
py_in_win_exe-1.0.2.dist-info/METADATA
py_in_win_exe-1.0.2.dist-info/WHEEL
py_in_win_exe-1.0.2.dist-info/entry_points.txt
py_in_win_exe-1.0.2.dist-info/top_level.txt
py_in_win_exe-1.0.2.dist-info/RECORD
