Metadata-Version: 2.4
Name: py-in-win-exe
Version: 1.0.2
Summary: GUI и CLI инструмент для компиляции Python в EXE
Home-page: https://github.com/ваш-репозиторий/py-in-win-exe
Author: Vadim M.
Author-email: somerare22@gmail.com
License: MIT
Keywords: pyinstaller gui exe compiler
Classifier: Programming Language :: Python :: 3
Classifier: License :: OSI Approved :: MIT License
Classifier: Operating System :: Microsoft :: Windows
Requires-Python: >=3.6
License-File: LICENSE
Requires-Dist: pyinstaller>=5.0
Requires-Dist: tkinter>=0.1.0
Dynamic: author
Dynamic: author-email
Dynamic: classifier
Dynamic: description
Dynamic: description-content-type
Dynamic: home-page
Dynamic: keywords
Dynamic: license
Dynamic: license-file
Dynamic: requires-dist
Dynamic: requires-python
Dynamic: summary
